contrib/drforbin/verilog/verilog_modules/T_FF_TESTBENCH.v
/*module to test T type Flip Flop*/

module T_FF_TESTBENCH(q0, q1, q2, q3, clk, reset);

input  q0, q1, q2, q3;
output clk;
output reset;
reg clk, reset;

initial 
   clk = 1'b0;

always
   #5 clk = ~clk;

initial
   begin
      $dumpfile("test.vcd");
      $dumpvars(0,ripple);
      reset = 1'b1;
      #10 reset = 1'b0;
      #180 reset = 1'b1;
      #3 reset = 1'b0;
      #30 $finish;
   end

endmodule

netlist/examples/verilog/T_FF_example/verilog_modules/D_FF.v
// module for D_FF D-Flip Flop


module D_FF(q, d, clk, reset);

output q;
input d, clk, reset;
reg q;



	always @(posedge reset or negedge clk)
		if (reset)
			q = 1'b0;
		else
			q = d;

endmodule

netlist/examples/verilog/T_FF_example/verilog_modules/T_FF.v
/* module for T-Flip Flop */


module T_FF(q_, clock_, reset_);


output q_;
input clock_, reset_;
wire d;

D_FF dff0(q_, d, clock_, reset_);
	not n1(d, q_); //not primitive

endmodule

gnetlist/examples/verilog/T_FF_example/verilog_modules/RIPPLE_COUNT.v
/* structural Verilog generated by gnetlist */
/* WARNING: This is a generated file, edits */
/*        made here will be lost next time  */
/*        you run gnetlist!                 */
/* Id ..........$Id$ */
/* Source.......$Source$ */
/* Revision.....$Revision$ */
/* Author.......$Author$ */

module RIPPLE_COUNT (
       reset ,
       clock ,
       q3 ,
       q2 ,
       q1 ,
       q0
      );

/* Port directions begin here */
input reset ;
input clock ;
output q3 ;
output q2 ;
output q1 ;
output q0 ;


/* Wires from the design */
wire reset ;
wire q3 ;
wire q2 ;
wire q1 ;
wire q0 ;
wire clock ;

/* continuous assignments */

/* Package instantiations */
T_FF U1 ( 
    .clock_ ( clock ),
    .reset_ ( reset ),
    .q_ ( q0 )
    );

T_FF U2 ( 
    .clock_ ( q0 ),
    .reset_ ( reset ),
    .q_ ( q1 )
    );

T_FF U3 ( 
    .clock_ ( q1 ),
    .reset_ ( reset ),
    .q_ ( q2 )
    );

T_FF U4 ( 
    .clock_ ( q2 ),
    .reset_ ( reset ),
    .q_ ( q3 )
    );

endmodule

gnetlist/examples/verilog/T_FF_example/dummy_test.v
//dummy moudle for test bench


module dummy;

wire q0,q1,q2,q3,clk,reset;

   RIPPLE_COUNT ripple(.q0(q0),.q1(q1),.q2(q2),.q3(q3),
   .clock(clk),.reset(reset));
   T_FF_TESTBENCH TB1(.q0(q0),.q1(q1),.q2(q2),.q3(q3),
   .clk(clk),.reset(reset));

endmodule

contrib/drforbin/verilog/test.vcd
$date
	Sun Aug  6 15:36:29 2017
$end
$version
	Icarus Verilog
$end
$timescale
	1s
$end
$scope module dummy $end
$scope module ripple $end
$var wire 1 ! clock $end
$var wire 1 " q0 $end
$var wire 1 # q1 $end
$var wire 1 $ q2 $end
$var wire 1 % q3 $end
$var wire 1 & reset $end
$scope module U1 $end
$var wire 1 ! clock_ $end
$var wire 1 ' d $end
$var wire 1 " q_ $end
$var wire 1 & reset_ $end
$scope module dff0 $end
$var wire 1 ! clk $end
$var wire 1 ' d $end
$var wire 1 & reset $end
$var reg 1 ( q $end
$upscope $end
$upscope $end
$scope module U2 $end
$var wire 1 " clock_ $end
$var wire 1 ) d $end
$var wire 1 # q_ $end
$var wire 1 & reset_ $end
$scope module dff0 $end
$var wire 1 " clk $end
$var wire 1 ) d $end
$var wire 1 & reset $end
$var reg 1 * q $end
$upscope $end
$upscope $end
$scope module U3 $end
$var wire 1 # clock_ $end
$var wire 1 + d $end
$var wire 1 $ q_ $end
$var wire 1 & reset_ $end
$scope module dff0 $end
$var wire 1 # clk $end
$var wire 1 + d $end
$var wire 1 & reset $end
$var reg 1 , q $end
$upscope $end
$upscope $end
$scope module U4 $end
$var wire 1 $ clock_ $end
$var wire 1 - d $end
$var wire 1 % q_ $end
$var wire 1 & reset_ $end
$scope module dff0 $end
$var wire 1 $ clk $end
$var wire 1 - d $end
$var wire 1 & reset $end
$var reg 1 . q $end
$upscope $end
$upscope $end
$upscope $end
$upscope $end
$enddefinitions $end
#0
$dumpvars
0.
1-
0,
1+
0*
1)
0(
1'
1&
0%
0$
0#
0"
0!
$end
#5
1!
#10
0'
1(
1"
0!
0&
#15
1!
#20
0)
1'
1*
1#
0(
0"
0!
#25
1!
#30
0'
1(
1"
0!
#35
1!
#40
0+
1)
1,
1$
1'
0*
0#
0(
0"
0!
#45
1!
#50
0'
1(
1"
0!
#55
1!
#60
0)
1'
1*
1#
0(
0"
0!
#65
1!
#70
0'
1(
1"
0!
#75
1!
#80
0-
1+
1.
1%
1)
0,
0$
1'
0*
0#
0(
0"
0!
#85
1!
#90
0'
1(
1"
0!
#95
1!
#100
0)
1'
1*
1#
0(
0"
0!
#105
1!
#110
0'
1(
1"
0!
#115
1!
#120
0+
1)
1,
1$
1'
0*
0#
0(
0"
0!
#125
1!
#130
0'
1(
1"
0!
#135
1!
#140
0)
1'
1*
1#
0(
0"
0!
#145
1!
#150
0'
1(
1"
0!
#155
1!
#160
1-
1+
0.
0%
1)
0,
0$
1'
0*
0#
0(
0"
0!
#165
1!
#170
0'
1(
1"
0!
#175
1!
#180
0)
1'
1*
1#
0(
0"
0!
#185
1!
#190
1)
0*
0#
0!
1&
#193
0&
#195
1!
#200
0'
1(
1"
0!
#205
1!
#210
0)
1'
1*
1#
0(
0"
0!
#215
1!
#220
0'
1(
1"
0!
